LICENSE
MANIFEST.in
README.md
requirements.txt
setup.py
src/ReadLammpsTraj.py
src/ReadLammpsTraj.egg-info/PKG-INFO
src/ReadLammpsTraj.egg-info/SOURCES.txt
src/ReadLammpsTraj.egg-info/dependency_links.txt
src/ReadLammpsTraj.egg-info/requires.txt
src/ReadLammpsTraj.egg-info/top_level.txt
src/utils/__init__.py
src/utils/hbonds.py
src/utils/water.py