Metadata-Version: 2.1
Name: ReadLammpsTraj
Version: 1.2.4
Summary: Read lammps dump trajectory.
Home-page: https://github.com/eastsheng/ReadLammpsTraj
Author: CHENDONGSHENG
Author-email: eastsheng@hotmail.com
License-File: LICENSE
Requires-Dist: numpy>=1.24.3
Requires-Dist: pandas>=2.0.3
Requires-Dist: tqdm>=4.66.1
Requires-Dist: periodictable>=1.6.1
Requires-Dist: readlammpsdata>=1.0.9
Requires-Dist: scipy>=1.13.1
